data_pack_importer_compare-0.0.5.dist-info/DESCRIPTION.rst
data_pack_importer_compare-0.0.5.dist-info/METADATA
data_pack_importer_compare-0.0.5.dist-info/RECORD
data_pack_importer_compare-0.0.5.dist-info/WHEEL
data_pack_importer_compare-0.0.5.dist-info/entry_points.txt
data_pack_importer_compare-0.0.5.dist-info/metadata.json
data_pack_importer_compare-0.0.5.dist-info/top_level.txt
dpic/__init__.py
dpic/__version__.py
dpic/compare.py
