Metadata-Version: 2.0
Name: data-pack-importer-compare
Version: 0.0.5
Summary: Command-line validation for datapack import
Home-page: https://github.com/davidhuser/data-pack-importer-compare
Author: David Huser
Author-email: dhuser@baosystems.com
License: BSD3
Keywords: datim
Platform: UNKNOWN
Classifier: License :: OSI Approved :: BSD License
Classifier: Programming Language :: Python
Classifier: Programming Language :: Python :: 2.7
Classifier: Programming Language :: Python :: 3.5
Classifier: Programming Language :: Python :: 3.6
Requires-Dist: pandas
